{
    "definition": "Describing an optic fibre used for optogenetics.",
    "identifier": "mikkel_optic_fibre",
    "name": "OpticFibre",
    "notes": {
        "value": ""
    },
    "optic_fibre_description": {
        "definition": "Description of the optic fibre.",
        "value": "Uncleaved Fiber Optic Cannula, \u00d82.5 mm Stainless Ferrule, \u00d8200 \u00b5m Core, 0.39 NA, 20 Pack"
    },
    "optic_fibre_diameter": {
        "unit": "um",
        "value": [
            200.0
        ]
    },
    "optic_fibre_manufacturer": {
        "definition": "The manufacturer of the optic fibre.",
        "value": "Thor labs"
    },
    "optic_fibre_serial_num": {
        "definition": "The serial number of the optic fibre.",
        "value": "CFM12U-20"
    }
}