{
    "definition": "Properties for describing an electrophysiological experiment.",
    "identifier": "experiment_electrophysiology",
    "subtype": {
        "alternatives": [
            "dual electrode recording",
            "multi electrode recording",
            "single electrode recording"
        ],
        "definition": "Subtype of this electrophysiological experiment.",
        "value": ""
    },
    "type": {
        "alternatives": [
            "EEG",
            "EKG",
            "EMG",
            "ERG",
            "extracellular recording",
            "intracellular recording",
            "loose patch",
            "patch clamp",
            "whole cell patch"
        ],
        "definition": "Intracellular recording of single cell responses with sharp microelectrodes.",
        "value": ""
    }
}